moretunes/apple/__init__.py
moretunes/apple/main.py
moretunes/apple/models.py
moretunes/apple/token.py
moretunes/apple/methods/__init__.py
moretunes/apple/methods/activities.py
moretunes/apple/methods/albums.py
moretunes/apple/methods/apple_music_api.py
moretunes/apple/methods/apple_music_stations.py
moretunes/apple/methods/artists.py
moretunes/apple/methods/charts.py
moretunes/apple/methods/curators.py
moretunes/apple/methods/history.py
moretunes/apple/methods/music_genres.py
moretunes/apple/methods/music_videos.py
moretunes/apple/methods/playlists.py
moretunes/apple/methods/ratings.py
moretunes/apple/methods/recommendations.py
moretunes/apple/methods/record_labels.py
moretunes/apple/methods/search.py
moretunes/apple/methods/songs.py
moretunes/apple/methods/storefronts_localization.py
moretunes/apple/simple/__init__.py
moretunes/apple/simple/main.py
moretunes_apple-1.3.1rc12.dev1.dist-info/LICENSE
moretunes_apple-1.3.1rc12.dev1.dist-info/METADATA
moretunes_apple-1.3.1rc12.dev1.dist-info/WHEEL
moretunes_apple-1.3.1rc12.dev1.dist-info/top_level.txt
moretunes_apple-1.3.1rc12.dev1.dist-info/RECORD
