Metadata-Version: 2.1
Name: moretunes-apple
Version: 1.3.1rc12.dev1
Summary: fully featured python wrapper for the Apple Music API
Author-email: jcbirdwell <jcbirdwell@gmail.com>
License: MIT License
Project-URL: repository, https://github.com/jcbirdwell/mt_apple_music_api
Classifier: Programming Language :: Python :: 3
Classifier: License :: OSI Approved :: MIT License
Classifier: Development Status :: 3 - Alpha
Requires-Python: >=3.12
License-File: LICENSE
Requires-Dist: cryptography
Requires-Dist: requests
Requires-Dist: pydantic
Requires-Dist: PyJWT
